whoisxml/__init__.py
whoisxml/cli.py
whoisxml/whoisxml.py
whoisxml-0.0.2.dist-info/LICENSE
whoisxml-0.0.2.dist-info/METADATA
whoisxml-0.0.2.dist-info/WHEEL
whoisxml-0.0.2.dist-info/entry_points.txt
whoisxml-0.0.2.dist-info/top_level.txt
whoisxml-0.0.2.dist-info/RECORD
